aics_dask_utils/__init__.py
aics_dask_utils/distributed_handler.py
aics_dask_utils-0.2.4.dist-info/LICENSE
aics_dask_utils-0.2.4.dist-info/METADATA
aics_dask_utils-0.2.4.dist-info/WHEEL
aics_dask_utils-0.2.4.dist-info/top_level.txt
aics_dask_utils-0.2.4.dist-info/RECORD
