Metadata-Version: 2.1
Name: aics-dask-utils
Version: 0.2.4
Summary: Utility functions and documentation related to Dask and AICS
Home-page: https://github.com/AllenCellModeling/aics_dask_utils
Author: Jackson Maxfield Brown
Author-email: jacksonb@alleninstitute.org
License: Allen Institute Software License
Keywords: aics_dask_utils
Platform: UNKNOWN
Classifier: Development Status :: 2 - Pre-Alpha
Classifier: Intended Audience :: Developers
Classifier: License :: Free for non-commercial use
Classifier: Natural Language :: English
Classifier: Programming Language :: Python :: 3.6
Classifier: Programming Language :: Python :: 3.7
Classifier: Programming Language :: Python :: 3.8
Requires-Python: >=3.6
Requires-Dist: distributed >=2.19.0
Provides-Extra: all
Requires-Dist: distributed >=2.19.0 ; extra == 'all'
Requires-Dist: codecov ; extra == 'all'
Requires-Dist: flake8 ; extra == 'all'
Requires-Dist: black ; extra == 'all'
Requires-Dist: pytest ; extra == 'all'
Requires-Dist: pytest-cov ; extra == 'all'
Requires-Dist: pytest-raises ; extra == 'all'
Requires-Dist: pytest-runner ; extra == 'all'
Requires-Dist: black >=19.10b0 ; extra == 'all'
Requires-Dist: bumpversion >=0.5.3 ; extra == 'all'
Requires-Dist: coverage >=5.0a4 ; extra == 'all'
Requires-Dist: flake8 >=3.7.7 ; extra == 'all'
Requires-Dist: ipython >=7.5.0 ; extra == 'all'
Requires-Dist: m2r >=0.2.4 ; extra == 'all'
Requires-Dist: pytest >=4.3.0 ; extra == 'all'
Requires-Dist: pytest-cov ==2.6.1 ; extra == 'all'
Requires-Dist: pytest-raises >=0.10 ; extra == 'all'
Requires-Dist: pytest-runner >=4.4 ; extra == 'all'
Requires-Dist: Sphinx <3,>=2.0.0b1 ; extra == 'all'
Requires-Dist: sphinx-rtd-theme >=0.1.2 ; extra == 'all'
Requires-Dist: tox >=3.5.2 ; extra == 'all'
Requires-Dist: twine >=1.13.0 ; extra == 'all'
Requires-Dist: wheel >=0.33.1 ; extra == 'all'
Requires-Dist: altair ; extra == 'all'
Requires-Dist: jupyterlab ; extra == 'all'
Requires-Dist: matplotlib ; extra == 'all'
Requires-Dist: aicsimageio >=3.2.0 ; extra == 'all'
Requires-Dist: bokeh >=2.0.2 ; extra == 'all'
Requires-Dist: dask >=2.16.0 ; extra == 'all'
Requires-Dist: dask-jobqueue >=0.7.1 ; extra == 'all'
Requires-Dist: imageio >=2.8.0 ; extra == 'all'
Provides-Extra: deepcheck
Requires-Dist: aicsimageio >=3.2.0 ; extra == 'deepcheck'
Requires-Dist: bokeh >=2.0.2 ; extra == 'deepcheck'
Requires-Dist: dask >=2.16.0 ; extra == 'deepcheck'
Requires-Dist: dask-jobqueue >=0.7.1 ; extra == 'deepcheck'
Requires-Dist: imageio >=2.8.0 ; extra == 'deepcheck'
Provides-Extra: dev
Requires-Dist: black >=19.10b0 ; extra == 'dev'
Requires-Dist: bumpversion >=0.5.3 ; extra == 'dev'
Requires-Dist: coverage >=5.0a4 ; extra == 'dev'
Requires-Dist: flake8 >=3.7.7 ; extra == 'dev'
Requires-Dist: ipython >=7.5.0 ; extra == 'dev'
Requires-Dist: m2r >=0.2.4 ; extra == 'dev'
Requires-Dist: pytest >=4.3.0 ; extra == 'dev'
Requires-Dist: pytest-cov ==2.6.1 ; extra == 'dev'
Requires-Dist: pytest-raises >=0.10 ; extra == 'dev'
Requires-Dist: pytest-runner >=4.4 ; extra == 'dev'
Requires-Dist: Sphinx <3,>=2.0.0b1 ; extra == 'dev'
Requires-Dist: sphinx-rtd-theme >=0.1.2 ; extra == 'dev'
Requires-Dist: tox >=3.5.2 ; extra == 'dev'
Requires-Dist: twine >=1.13.0 ; extra == 'dev'
Requires-Dist: wheel >=0.33.1 ; extra == 'dev'
Provides-Extra: interactive
Requires-Dist: altair ; extra == 'interactive'
Requires-Dist: jupyterlab ; extra == 'interactive'
Requires-Dist: matplotlib ; extra == 'interactive'
Provides-Extra: setup
Requires-Dist: pytest-runner ; extra == 'setup'
Provides-Extra: test
Requires-Dist: codecov ; extra == 'test'
Requires-Dist: flake8 ; extra == 'test'
Requires-Dist: black ; extra == 'test'
Requires-Dist: pytest ; extra == 'test'
Requires-Dist: pytest-cov ; extra == 'test'
Requires-Dist: pytest-raises ; extra == 'test'
